fuelai/__init__.py
fuelai/answers.py
fuelai/api_client.py
fuelai/errors_extensions.py
fuelai/projects.py
fuelai/tasks.py
fuelai_python_sdk-1.0.3.dist-info/LICENSE
fuelai_python_sdk-1.0.3.dist-info/METADATA
fuelai_python_sdk-1.0.3.dist-info/WHEEL
fuelai_python_sdk-1.0.3.dist-info/top_level.txt
fuelai_python_sdk-1.0.3.dist-info/RECORD
