Metadata-Version: 2.1
Name: fuelai-python-sdk
Version: 1.0.3
Summary: Fuel AI Python SDK
Home-page: https://github.com/FuelHQ-Public/fuelai-python
Author: Fuel AI
Author-email: technology@fuelhq.ai
License: MIT
Platform: UNKNOWN
Requires-Python: >=3.6
License-File: LICENSE
Requires-Dist: requests (~=2.25)
Requires-Dist: python-dateutil (~=2.8.1)
